kwsgi/__init__.py
kwsgi/cli.py
kwsgi/daemonize.py
kwsgi/reloader.py
kwsgi/server.py
kwsgi-0.0.2.dist-info/METADATA
kwsgi-0.0.2.dist-info/RECORD
kwsgi-0.0.2.dist-info/WHEEL
kwsgi-0.0.2.dist-info/entry_points.txt
kwsgi-0.0.2.dist-info/top_level.txt
